LICENSE
MANIFEST.in
README.rst
setup.py
pytest_django_model/__init__.py
pytest_django_model/core.py
pytest_django_model/file.py
pytest_django_model/objects.py
pytest_django_model/plugin.py
pytest_django_model/utils.py
pytest_django_model.egg-info/PKG-INFO
pytest_django_model.egg-info/SOURCES.txt
pytest_django_model.egg-info/dependency_links.txt
pytest_django_model.egg-info/entry_points.txt
pytest_django_model.egg-info/requires.txt
pytest_django_model.egg-info/top_level.txt