Metadata-Version: 1.2
Name: pytest-django-model
Version: 0.1.9
Summary: A Simple Way to Test your Django Models
Home-page: https://github.com/kmarilleau/pytest-django-model
Author: Kevin Marilleau
Author-email: kevin.marilleau@gmail.com
Maintainer: Kevin Marilleau
Maintainer-email: kevin.marilleau@gmail.com
License: GNU GPL v3.0
Platform: UNKNOWN
Classifier: Development Status :: 4 - Beta
Classifier: Framework :: Pytest
Classifier: Intended Audience :: Developers
Classifier: Topic :: Software Development :: Testing
Classifier: Programming Language :: Python
Classifier: Programming Language :: Python :: 3.5
Classifier: Programming Language :: Python :: 3.6
Classifier: Programming Language :: Python :: 3.7
Classifier: Programming Language :: Python :: Implementation :: CPython
Classifier: Programming Language :: Python :: Implementation :: PyPy
Classifier: Operating System :: OS Independent
Classifier: License :: OSI Approved :: GNU General Public License v3 (GPLv3)
Requires-Python: >=2.7, !=3.0.*, !=3.1.*, !=3.2.*, !=3.3.*
